akimgtransmitter/__init__.py
akimgtransmitter/core.py
akimgtransmitter-0.1.0.dist-info/METADATA
akimgtransmitter-0.1.0.dist-info/WHEEL
akimgtransmitter-0.1.0.dist-info/top_level.txt
akimgtransmitter-0.1.0.dist-info/RECORD
