Metadata-Version: 2.4
Name: akimgtransmitter
Version: 0.1.0
Summary: Simple image/frame transmitter that saves latest frame to a folder.
Author: Akshay ajit bhawar
Requires-Python: >=3.7
Dynamic: author
Dynamic: requires-python
Dynamic: summary
